LICENSE
MANIFEST.in
README.md
setup.cfg
setup.py
rice_manager/__init__.py
rice_manager/add_rices.py
rice_manager/main_menu.py
rice_manager/utils.py
rice_manager/view_rices.py
rice_manager.egg-info/PKG-INFO
rice_manager.egg-info/SOURCES.txt
rice_manager.egg-info/dependency_links.txt
rice_manager.egg-info/entry_points.txt
rice_manager.egg-info/requires.txt
rice_manager.egg-info/top_level.txt
rice_manager/data/css/style.css
rice_manager/data/icons/rice-manager-translucent.png
rice_manager/data/icons/rice-manager.png